LICENSE
MANIFEST.in
README.rst
RELEASE-VERSION
setup.py
gitpy_versioning/.git
gitpy_versioning/.gitignore
gitpy_versioning/README.md
gitpy_versioning/__init__.py
gitpy_versioning/__init__.pyc
gitpy_versioning/test_gitpy_versioning.py
steelscript/__init__.py
steelscript.appfwk.business_hours.egg-info/PKG-INFO
steelscript.appfwk.business_hours.egg-info/SOURCES.txt
steelscript.appfwk.business_hours.egg-info/dependency_links.txt
steelscript.appfwk.business_hours.egg-info/entry_points.txt
steelscript.appfwk.business_hours.egg-info/namespace_packages.txt
steelscript.appfwk.business_hours.egg-info/requires.txt
steelscript.appfwk.business_hours.egg-info/top_level.txt
steelscript/appfwk/__init__.py
steelscript/appfwk/business_hours/__init__.py
steelscript/appfwk/business_hours/models.py
steelscript/appfwk/business_hours/plugin.py
steelscript/appfwk/business_hours/datasource/__init__.py
steelscript/appfwk/business_hours/datasource/business_hours_source.py
steelscript/appfwk/business_hours/reports/__init__.py
steelscript/appfwk/business_hours/reports/business_hours_report.py
steelscript/appfwk/business_hours/reports/business_hours_report_byapp.py