Metadata-Version: 1.1
Name: steelscript.appfwk.business-hours
Version: 0.9.7
Summary: Business-Hours plugin for SteelScript Application Framework
Home-page: http://pythonhosted.org/steelscript
Author: Riverbed Technology
Author-email: eng-github@riverbed.com
License: MIT
Platform: Linux
Platform: Mac OS
Platform: Windows
Classifier: Development Status :: 4 - Beta
Classifier: Intended Audience :: Developers
Classifier: Intended Audience :: Information Technology
Classifier: Intended Audience :: System Administrators
Classifier: License :: OSI Approved :: MIT License
Classifier: Programming Language :: Python :: 2.6
Classifier: Programming Language :: Python :: 2.7
Classifier: Topic :: System :: Networking
